rapidTk/__init__.py
rapidTk/__main__.py
rapidTk/cWidgets.py
rapidTk/cWidgets_extended.py
rapidTk/flags.py
rapidTk/language.py
rapidTk/matchart.py
rapidTk/rTkErrors.py
rapidTk/rTkForm.py
rapidTk/rTkLogging.py
rapidTk/rTkManagers.py
rapidTk/rTkOverrides.py
rapidTk/rTkTheme.py
rapidTk/rTkUtils.py
rapidTk/reWidgets.py
rapidTk/assets/cur.cur
rapidTk/assets/local/en_gb.xml
rapidTk/assets/local/fr.xml
rapidTk/assets/rapidTk.egg-info/PKG-INFO
rapidTk/assets/rapidTk.egg-info/SOURCES.txt
rapidTk/assets/rapidTk.egg-info/dependency_links.txt
rapidTk/assets/rapidTk.egg-info/top_level.txt
rapidTk/examples/examples_basic.py
rapidTk/examples/examples_extended.py
rapidTk/rTkCalendar/rTkCalendar.py
rapidTk/testing/attr_test.py
rapidTk/testing/date_format_test.py
rapidTk/testing/inline_layout_test.py
rapidTk/testing/logging_testing.py
rapidTk/testing/options_bug.py
rapidTk/testing/sp_test.py
rapidTk/testing/st_tst.py
rapidTk/testing/stack.py
rapidTk/testing/styling.py
rapidTk/testing/syn.py
rapidTk/testing/test_combobox.py
rapidTk/testing/treeview_and_DateEntry.py
rapidTk-0.0.7.dist-info/LICENSE
rapidTk-0.0.7.dist-info/METADATA
rapidTk-0.0.7.dist-info/WHEEL
rapidTk-0.0.7.dist-info/top_level.txt
rapidTk-0.0.7.dist-info/RECORD
