Metadata-Version: 2.1
Name: rapidTk
Version: 0.0.7
Summary: A wrapper for quickly creating Tkinter code
Author-email: Scott Paterson <scott_j_paterson@hotmail.co.uk>
License: MIT License
Project-URL: Homepage, https://github.com/AceScottie/RapidTk
Classifier: Programming Language :: Python :: 3
Classifier: License :: OSI Approved :: MIT License
Classifier: Operating System :: Microsoft :: Windows
Requires-Python: >=3.0
License-File: LICENSE
